Seq_logic/T_flipflop/T_ff.vhd
library ieee;
use ieee.std_logic_1164.all;


entity T_ff is
    port
    (
        T, CLK, RST : in std_logic;
        Q, Qbar : out std_logic
    );
end entity;

architecture behavioural of T_ff is
begin

    process(CLK,RST) is
    variable m : std_logic := '0';
    begin
        if(RST = '1') then m:='0';
        elsif(falling_edge(CLK)) then
            if(T = '0') then m:=m;
            elsif(T = '1') then m:= not m;
            else null;
            end if;
        end if;

        Q <= m;
        Qbar <= not m;
        
    end process;

 

end architecture;

counters/sync/upcount_4bit/sync_upcount.vhd
library ieee;
use ieee.std_logic_1164.all;

entity sync_upcount is
    port
    (
        Clk_in, Rst : in std_logic;
        COUNT : out std_ulogic_vector(3 downto 0)
    );

end entity;

architecture rtl of sync_upcount is

component T_ff
    port
    (
        T, CLK, RST : in std_logic;
        Q, Qbar : out std_logic
    );
end component;

signal t1, t2, t3, t4 : std_ulogic;
signal cnt, cnt_bar : std_ulogic_vector(3 downto 0);

begin

    tff1: T_ff port map
        (
            T => t1,
            CLK => Clk_in,
            RST => Rst,
            Q => cnt(0),
            Qbar => cnt_bar(0)
        );

    tff2: T_ff port map
        (
            T => t2,
            CLK => Clk_in,
            RST => Rst,
            Q => cnt(1),
            Qbar => cnt_bar(1)
        );

    tff3: T_ff port map
        (
            T => t3,
            CLK => Clk_in,
            RST => Rst,
            Q => cnt(2),
            Qbar => cnt_bar(2)
        );
    
    tff4: T_ff port map
        (
            T => t4,
            CLK => Clk_in,
            RST => Rst,
            Q => cnt(3),
            Qbar => cnt_bar(3)
        );

    t1 <= '1';
    t2 <= cnt(0);
    t3 <= cnt(1) and cnt(0);
    t4 <= cnt(0) and cnt(1) and cnt(2);

    COUNT <= cnt;



end architecture;

Combinational/counters/sync/upcount_4bit/sync_upcount_tb.vhd
library ieee;
use ieee.std_logic_1164.all;

entity sync_upcount_tb is
end entity;

architecture testbench of sync_upcount_tb is

component sync_upcount
port
    (
        Clk_in, Rst : in std_logic;
        COUNT : out std_ulogic_vector(3 downto 0)
    );
end component;

signal Clk_in, Rst : std_logic;
signal COUNT : std_ulogic_vector(3 downto 0);


begin 

    UUT: sync_upcount port map
    (
        Clk_in => Clk_in,
        Rst => Rst,
        COUNT => COUNT
    );

    Rst <= '1';


    clock_proc: process
    begin
        for ii in 0 to 16 loop
            clk_in <= '0';
            wait for 10 ns;
            clk_in <= '1';
            wait for 10 ns;
        end loop;

        wait;
    end process;


end architecture;

counters/sync/upcount_4bit/sync_upcount.vcd
$date
  Mon Mar 15 20:30:05 2021
$end
$version
  GHDL v0
$end
$timescale
  1 fs
$end
$scope module standard $end
$upscope $end
$scope module std_logic_1164 $end
$upscope $end
$scope module sync_upcount_tb $end
$var reg 1 ! clk_in $end
$var reg 1 " rst $end
$var reg 4 # count[3:0] $end
$scope module uut $end
$var reg 1 $ clk_in $end
$var reg 1 % rst $end
$var reg 4 & count[3:0] $end
$var reg 1 ' t1 $end
$var reg 1 ( t2 $end
$var reg 1 ) t3 $end
$var reg 1 * t4 $end
$var reg 4 + cnt[3:0] $end
$var reg 4 , cnt_bar[3:0] $end
$scope module tff1 $end
$var reg 1 - t $end
$var reg 1 . clk $end
$var reg 1 / rst $end
$var reg 1 0 q $end
$var reg 1 1 qbar $end
$upscope $end
$scope module tff2 $end
$var reg 1 2 t $end
$var reg 1 3 clk $end
$var reg 1 4 rst $end
$var reg 1 5 q $end
$var reg 1 6 qbar $end
$upscope $end
$scope module tff3 $end
$var reg 1 7 t $end
$var reg 1 8 clk $end
$var reg 1 9 rst $end
$var reg 1 : q $end
$var reg 1 ; qbar $end
$upscope $end
$scope module tff4 $end
$var reg 1 < t $end
$var reg 1 = clk $end
$var reg 1 > rst $end
$var reg 1 ? q $end
$var reg 1 @ qbar $end
$upscope $end
$upscope $end
$upscope $end
$enddefinitions $end
#0
0!
1"
b0000 #
0$
1%
b0000 &
1'
0(
0)
0*
b0000 +
b1111 ,
1-
0.
1/
00
11
02
03
14
05
16
07
08
19
0:
1;
0<
0=
1>
0?
1@
#10000000
1!
1$
1.
13
18
1=
#20000000
0!
b0001 #
0$
b0001 &
1(
b0001 +
b1110 ,
0.
10
01
12
03
08
0=
#30000000
1!
1$
1.
13
18
1=
#40000000
0!
b0010 #
0$
b0010 &
0(
b0010 +
b1101 ,
0.
00
11
02
03
15
06
08
0=
#50000000
1!
1$
1.
13
18
1=
#60000000
0!
b0011 #
0$
b0011 &
1(
1)
b0011 +
b1100 ,
0.
10
01
12
03
17
08
0=
#70000000
1!
1$
1.
13
18
1=
#80000000
0!
b0100 #
0$
b0100 &
0(
0)
b0100 +
b1011 ,
0.
00
11
02
03
05
16
07
08
1:
0;
0=
#90000000
1!
1$
1.
13
18
1=
#100000000
0!
b0101 #
0$
b0101 &
1(
b0101 +
b1010 ,
0.
10
01
12
03
08
0=
#110000000
1!
1$
1.
13
18
1=
#120000000
0!
b0110 #
0$
b0110 &
0(
b0110 +
b1001 ,
0.
00
11
02
03
15
06
08
0=
#130000000
1!
1$
1.
13
18
1=
#140000000
0!
b0111 #
0$
b0111 &
1(
1)
1*
b0111 +
b1000 ,
0.
10
01
12
03
17
08
1<
0=
#150000000
1!
1$
1.
13
18
1=
#160000000
0!
b1000 #
0$
b1000 &
0(
0)
0*
b1000 +
b0111 ,
0.
00
11
02
03
05
16
07
08
0:
1;
0<
0=
1?
0@
#170000000
1!
1$
1.
13
18
1=
#180000000
0!
b1001 #
0$
b1001 &
1(
b1001 +
b0110 ,
0.
10
01
12
03
08
0=
#190000000
1!
1$
1.
13
18
1=
#200000000
0!
b1010 #
0$
b1010 &
0(
b1010 +
b0101 ,
0.
00
11
02
03
15
06
08
0=
#210000000
1!
1$
1.
13
18
1=
#220000000
0!
b1011 #
0$
b1011 &
1(
1)
b1011 +
b0100 ,
0.
10
01
12
03
17
08
0=
#230000000
1!
1$
1.
13
18
1=
#240000000
0!
b1100 #
0$
b1100 &
0(
0)
b1100 +
b0011 ,
0.
00
11
02
03
05
16
07
08
1:
0;
0=
#250000000
1!
1$
1.
13
18
1=
#260000000
0!
b1101 #
0$
b1101 &
1(
b1101 +
b0010 ,
0.
10
01
12
03
08
0=
#270000000
1!
1$
1.
13
18
1=
#280000000
0!
b1110 #
0$
b1110 &
0(
b1110 +
b0001 ,
0.
00
11
02
03
15
06
08
0=
#290000000
1!
1$
1.
13
18
1=
#300000000
0!
b1111 #
0$
b1111 &
1(
1)
1*
b1111 +
b0000 ,
0.
10
01
12
03
17
08
1<
0=
#310000000
1!
1$
1.
13
18
1=
#320000000
0!
b0000 #
0$
b0000 &
0(
0)
0*
b0000 +
b1111 ,
0.
00
11
02
03
05
16
07
08
0:
1;
0<
0=
0?
1@
