Seq_logic/T_flipflop/T_ff.vhd
library ieee;
use ieee.std_logic_1164.all;


entity T_ff is
    port
    (
        T, CLK, RST : in std_logic;
        Q, Qbar : out std_logic
    );
end entity;

architecture behavioural of T_ff is
begin

    process(CLK,RST) is
    variable m : std_logic := '0';
    begin
        if(RST = '1') then m:='0';
        elsif(falling_edge(CLK)) then
            if(T = '0') then m:=m;
            elsif(T = '1') then m:= not m;
            else null;
            end if;
        end if;

        Q <= m;
        Qbar <= not m;
        
    end process;

 

end architecture;

counters/async/down_counter/down_counter.vhd
library ieee;
use ieee.std_logic_1164.all;

entity down_counter is
    port
    (
        Clk_in, Rst : in std_logic;
        Q, Qbar : out std_logic_vector(3 downto 0)
    );
end entity;

architecture dataflow of down_counter is

component T_ff
    port
    (
        T, CLK, RST : in std_logic;
        Q, Qbar : out std_logic
    );

end component;


signal t : std_logic_vector(3 downto 0) := "1111";
signal qff, qff_bar: std_logic_vector(3 downto 0);

begin

    ff1 : T_ff port map
        (
            T => t(0),
            CLK => Clk_in,
            RST => Rst,
            Q => qff(0),
            Qbar => qff_bar(0)
        );

    ff2 : T_ff port map
        (
            T => t(1),
            CLK => qff_bar(0),
            RST => Rst,
            Q => qff(1),
            Qbar => qff_bar(1)
        );

    ff3 : T_ff port map
        (
            T => t(2),
            CLK => qff_bar(1),
            RST => Rst,
            Q => qff(2),
            Qbar => qff_bar(2)
        );
    
    ff4 : T_ff port map
        (
            T => t(3),
            CLK => qff_bar(2),
            RST => Rst,
            Q => qff(3),
            Qbar => qff_bar(3)
        );

    Q <= qff;
    Qbar <= qff_bar;



end architecture;

counters/async/down_counter/down_counter_tb.vhd
library ieee;
use ieee.std_logic_1164.all;

entity down_counter_tb is
end entity;

architecture testbench of down_counter_tb is

component down_counter
port
(
    Clk_in, Rst : in std_logic;
    Q, Qbar : out std_logic_vector(3 downto 0)
);
end component;

signal clk_in, rst: std_logic;
signal q, qbar: std_logic_vector(3 downto 0);

begin

    UUT : down_counter port map
    (
        Clk_in => clk_in,
        Rst => rst,
        Q => q,
        Qbar => qbar
    );

    rst <= '1';

    clock: process
    begin
        for ii in 1 to 16 loop
            clk_in <= '0';
            wait for 10 ns;
            clk_in <= '1';
            wait for 10 ns;
        end loop;

        wait;
    end process;



end architecture;

counters/async/down_counter/down_counter.vcd
$date
  Sun Mar 14 22:44:02 2021
$end
$version
  GHDL v0
$end
$timescale
  1 fs
$end
$scope module standard $end
$upscope $end
$scope module std_logic_1164 $end
$upscope $end
$scope module down_counter_tb $end
$var reg 1 ! clk_in $end
$var reg 1 " rst $end
$var reg 4 # q[3:0] $end
$var reg 4 $ qbar[3:0] $end
$scope module uut $end
$var reg 1 % clk_in $end
$var reg 1 & rst $end
$var reg 4 ' q[3:0] $end
$var reg 4 ( qbar[3:0] $end
$var reg 4 ) t[3:0] $end
$var reg 4 * qff[3:0] $end
$var reg 4 + qff_bar[3:0] $end
$scope module ff1 $end
$var reg 1 , t $end
$var reg 1 - clk $end
$var reg 1 . rst $end
$var reg 1 / q $end
$var reg 1 0 qbar $end
$upscope $end
$scope module ff2 $end
$var reg 1 1 t $end
$var reg 1 2 clk $end
$var reg 1 3 rst $end
$var reg 1 4 q $end
$var reg 1 5 qbar $end
$upscope $end
$scope module ff3 $end
$var reg 1 6 t $end
$var reg 1 7 clk $end
$var reg 1 8 rst $end
$var reg 1 9 q $end
$var reg 1 : qbar $end
$upscope $end
$scope module ff4 $end
$var reg 1 ; t $end
$var reg 1 < clk $end
$var reg 1 = rst $end
$var reg 1 > q $end
$var reg 1 ? qbar $end
$upscope $end
$upscope $end
$upscope $end
$enddefinitions $end
#0
0!
1"
b0000 #
b1111 $
0%
1&
b0000 '
b1111 (
b1111 )
b0000 *
b1111 +
1,
0-
1.
0/
10
11
12
13
04
15
16
17
18
09
1:
1;
1<
1=
0>
1?
#10000000
1!
1%
1-
#20000000
0!
b1111 #
b0000 $
0%
b1111 '
b0000 (
b1111 *
b0000 +
0-
1/
00
02
14
05
07
19
0:
0<
1>
0?
#30000000
1!
1%
1-
#40000000
0!
b1110 #
b0001 $
0%
b1110 '
b0001 (
b1110 *
b0001 +
0-
0/
10
12
#50000000
1!
1%
1-
#60000000
0!
b1101 #
b0010 $
0%
b1101 '
b0010 (
b1101 *
b0010 +
0-
1/
00
02
04
15
17
#70000000
1!
1%
1-
#80000000
0!
b1100 #
b0011 $
0%
b1100 '
b0011 (
b1100 *
b0011 +
0-
0/
10
12
#90000000
1!
1%
1-
#100000000
0!
b1011 #
b0100 $
0%
b1011 '
b0100 (
b1011 *
b0100 +
0-
1/
00
02
14
05
07
09
1:
1<
#110000000
1!
1%
1-
#120000000
0!
b1010 #
b0101 $
0%
b1010 '
b0101 (
b1010 *
b0101 +
0-
0/
10
12
#130000000
1!
1%
1-
#140000000
0!
b1001 #
b0110 $
0%
b1001 '
b0110 (
b1001 *
b0110 +
0-
1/
00
02
04
15
17
#150000000
1!
1%
1-
#160000000
0!
b1000 #
b0111 $
0%
b1000 '
b0111 (
b1000 *
b0111 +
0-
0/
10
12
#170000000
1!
1%
1-
#180000000
0!
b0111 #
b1000 $
0%
b0111 '
b1000 (
b0111 *
b1000 +
0-
1/
00
02
14
05
07
19
0:
0<
0>
1?
#190000000
1!
1%
1-
#200000000
0!
b0110 #
b1001 $
0%
b0110 '
b1001 (
b0110 *
b1001 +
0-
0/
10
12
#210000000
1!
1%
1-
#220000000
0!
b0101 #
b1010 $
0%
b0101 '
b1010 (
b0101 *
b1010 +
0-
1/
00
02
04
15
17
#230000000
1!
1%
1-
#240000000
0!
b0100 #
b1011 $
0%
b0100 '
b1011 (
b0100 *
b1011 +
0-
0/
10
12
#250000000
1!
1%
1-
#260000000
0!
b0011 #
b1100 $
0%
b0011 '
b1100 (
b0011 *
b1100 +
0-
1/
00
02
14
05
07
09
1:
1<
#270000000
1!
1%
1-
#280000000
0!
b0010 #
b1101 $
0%
b0010 '
b1101 (
b0010 *
b1101 +
0-
0/
10
12
#290000000
1!
1%
1-
#300000000
0!
b0001 #
b1110 $
0%
b0001 '
b1110 (
b0001 *
b1110 +
0-
1/
00
02
04
15
17
