Seq_logic/jk_flipflop/JK_ff.vhd
library ieee;
use ieee.std_logic_1164.all;

entity JK_ff is
    port
    (
        J, K, Rst, Clk : in std_logic;
        Q, Qb : out std_logic
    );

end entity;

architecture behavioural of JK_ff is

begin

    stim:   process(Clk,RST) is
            variable m : std_logic := '0';
            begin
                if(RST = '1') then m:= '0';

                elsif(rising_edge(Clk)) then

                    if(J='0' and K='0') then m:=m;
                    elsif(J='0' and K='1') then m:='0';
                    elsif(J='1' and K='1') then m:= not m;
                    else m:= '1';

                    end if;
                end if;

                Q <= m;
                Qb <= not m;
            end process;

end architecture;

Seq_logic/jk_flipflop/JK_ff_tb.vhd
library ieee;
use ieee.std_logic_1164.all;

entity JK_ff_tb is
end entity;

architecture testbench of JK_ff_tb is

component JK_ff
    port
    (
        J, K, Rst, Clk : in std_logic;
        Q, Qb : out std_logic
    );
end component;

signal j,k,rst,clk,q,qb : std_logic;


begin
    uut: JK_ff port map
    (
        J => j,
        K => k,
        Rst => rst,
        Clk => clk,
        Q => q,
        Qb => qb
    );

    --------------------------------------
    clock: process
    begin 
    for p in 1 to 6 loop
        clk <= '0';
        wait for 10 ns;
        clk <= '1';
        wait for 10 ns;
    end loop;
    wait;
    end process;

    ----------------------------------------

    stim: process
    begin
    rst <= '0';
    j <= '1';
    k <= '0';

    wait for 20 ns;
    ----------------------------------
    rst <= '0';
    j <= '0';
    k <= '1';

    wait for 20 ns;
    -----------------------------------
    rst <= '0';
    j <= '0';
    k <= '0';

    wait for 20 ns;
    -------------------------------------
    rst <= '0';
    j <= '1';
    k <= '1';

    wait for 20 ns;
    --------------------------------------
    rst <= '0';
    j <= '1';
    k <= '1';

    wait for 20 ns;
    ---------------------------------------
    rst <= '0';
    j <= '1';
    k <= '1';

    wait for 20 ns;

    wait;

    end process;

end architecture;

Seq_logic/jk_flipflop/JK_ff.vcd
$date
  Sun Mar 14 16:36:38 2021
$end
$version
  GHDL v0
$end
$timescale
  1 fs
$end
$scope module standard $end
$upscope $end
$scope module std_logic_1164 $end
$upscope $end
$scope module jk_ff_tb $end
$var reg 1 ! j $end
$var reg 1 " k $end
$var reg 1 # rst $end
$var reg 1 $ clk $end
$var reg 1 % q $end
$var reg 1 & qb $end
$scope module uut $end
$var reg 1 ' j $end
$var reg 1 ( k $end
$var reg 1 ) rst $end
$var reg 1 * clk $end
$var reg 1 + q $end
$var reg 1 , qb $end
$upscope $end
$upscope $end
$enddefinitions $end
#0
1!
0"
0#
0$
0%
1&
1'
0(
0)
0*
0+
1,
#10000000
1$
1%
0&
1*
1+
0,
#20000000
0!
1"
0$
0'
1(
0*
#30000000
1$
0%
1&
1*
0+
1,
#40000000
0"
0$
0(
0*
#50000000
1$
1*
#60000000
1!
1"
0$
1'
1(
0*
#70000000
1$
1%
0&
1*
1+
0,
#80000000
0$
0*
#90000000
1$
0%
1&
1*
0+
1,
#100000000
0$
0*
#110000000
1$
1%
0&
1*
1+
0,
