Seq_logic/T_flipflop/T_ff.vhd
library ieee;
use ieee.std_logic_1164.all;


entity T_ff is
    port
    (
        T, CLK, RST : in std_logic;
        Q, Qbar : out std_logic
    );
end entity;

architecture behavioural of T_ff is
begin

    process(CLK,RST) is
    variable m : std_logic := '0';
    begin
        if(RST = '1') then m:='0';
        elsif(falling_edge(CLK)) then
            if(T = '0') then m:=m;
            elsif(T = '1') then m:= not m;
            else null;
            end if;
        end if;

        Q <= m;
        Qbar <= not m;
        
    end process;

 

end architecture;

counters/sync/upcount_3bit/sync_upcount.vhd
library ieee;
use ieee.std_logic_1164.all;

entity sync_upcount is
    port
    (
        Clk_in, Rst : in std_logic;
        COUNT : out std_ulogic_vector(2 downto 0)
    );

end entity;

architecture rtl of sync_upcount is

component T_ff
    port
    (
        T, CLK, RST : in std_logic;
        Q, Qbar : out std_logic
    );
end component;

signal t1, t2, t3 : std_ulogic;
signal cnt, cnt_bar : std_ulogic_vector(2 downto 0);

begin

    tff1: T_ff port map
        (
            T => t1,
            CLK => Clk_in,
            RST => Rst,
            Q => cnt(0),
            Qbar => cnt_bar(0)
        );

    tff2: T_ff port map
        (
            T => t2,
            CLK => Clk_in,
            RST => Rst,
            Q => cnt(1),
            Qbar => cnt_bar(1)
        );

    tff3: T_ff port map
        (
            T => t3,
            CLK => Clk_in,
            RST => Rst,
            Q => cnt(2),
            Qbar => cnt_bar(2)
        );

    t1 <= '1';
    t2 <= cnt(0);
    t3 <= cnt(1) and cnt(0);

    COUNT <= cnt;



end architecture;

Combinational/counters/sync/upcount_3bit/sync_upcount_tb.vhd
library ieee;
use ieee.std_logic_1164.all;

entity sync_upcount_tb is
end entity;

architecture testbench of sync_upcount_tb is

component sync_upcount
port
    (
        Clk_in, Rst : in std_logic;
        COUNT : out std_ulogic_vector(2 downto 0)
    );
end component;

signal Clk_in, Rst : std_logic;
signal COUNT : std_ulogic_vector(2 downto 0);


begin 

    UUT: sync_upcount port map
    (
        Clk_in => Clk_in,
        Rst => Rst,
        COUNT => COUNT
    );

    Rst <= '1';


    clock_proc: process
    begin
        for ii in 1 to 8 loop
            clk_in <= '0';
            wait for 10 ns;
            clk_in <= '1';
            wait for 10 ns;
        end loop;

        wait;
    end process;


end architecture;

counters/sync/upcount_3bit/sync_upcount.vcd
$date
  Mon Mar 15 15:25:32 2021
$end
$version
  GHDL v0
$end
$timescale
  1 fs
$end
$scope module standard $end
$upscope $end
$scope module std_logic_1164 $end
$upscope $end
$scope module sync_upcount_tb $end
$var reg 1 ! clk_in $end
$var reg 1 " rst $end
$var reg 3 # count[2:0] $end
$scope module uut $end
$var reg 1 $ clk_in $end
$var reg 1 % rst $end
$var reg 3 & count[2:0] $end
$var reg 1 ' t1 $end
$var reg 1 ( t2 $end
$var reg 1 ) t3 $end
$var reg 3 * cnt[2:0] $end
$var reg 3 + cnt_bar[2:0] $end
$scope module tff1 $end
$var reg 1 , t $end
$var reg 1 - clk $end
$var reg 1 . rst $end
$var reg 1 / q $end
$var reg 1 0 qbar $end
$upscope $end
$scope module tff2 $end
$var reg 1 1 t $end
$var reg 1 2 clk $end
$var reg 1 3 rst $end
$var reg 1 4 q $end
$var reg 1 5 qbar $end
$upscope $end
$scope module tff3 $end
$var reg 1 6 t $end
$var reg 1 7 clk $end
$var reg 1 8 rst $end
$var reg 1 9 q $end
$var reg 1 : qbar $end
$upscope $end
$upscope $end
$upscope $end
$enddefinitions $end
#0
0!
1"
b000 #
0$
1%
b000 &
1'
0(
0)
b000 *
b111 +
1,
0-
1.
0/
10
01
02
13
04
15
06
07
18
09
1:
#10000000
1!
1$
1-
12
17
#20000000
0!
b001 #
0$
b001 &
1(
b001 *
b110 +
0-
1/
00
11
02
07
#30000000
1!
1$
1-
12
17
#40000000
0!
b010 #
0$
b010 &
0(
b010 *
b101 +
0-
0/
10
01
02
14
05
07
#50000000
1!
1$
1-
12
17
#60000000
0!
b011 #
0$
b011 &
1(
1)
b011 *
b100 +
0-
1/
00
11
02
16
07
#70000000
1!
1$
1-
12
17
#80000000
0!
b100 #
0$
b100 &
0(
0)
b100 *
b011 +
0-
0/
10
01
02
04
15
06
07
19
0:
#90000000
1!
1$
1-
12
17
#100000000
0!
b101 #
0$
b101 &
1(
b101 *
b010 +
0-
1/
00
11
02
07
#110000000
1!
1$
1-
12
17
#120000000
0!
b110 #
0$
b110 &
0(
b110 *
b001 +
0-
0/
10
01
02
14
05
07
#130000000
1!
1$
1-
12
17
#140000000
0!
b111 #
0$
b111 &
1(
1)
b111 *
b000 +
0-
1/
00
11
02
16
07
