Combinational/counters/async/updown_counter/counter.vhd
library ieee;
use ieee.std_logic_1164.all;
use ieee.numeric_std.all;



entity counter is
    port
    (
        Clk_in, Rst, Dir : in std_logic;
        COUNT: out std_ulogic_vector(3 downto 0)
    );
end entity;

architecture dataflow of counter is

signal cnt : unsigned(3 downto 0) := x"0";

begin

    count_proc: process(Clk_in, Rst) is

    begin
        if(Rst = '0') then cnt <= x"0";
        elsif(falling_edge(Clk_in)) then
            if(Dir = '0') then  
                cnt <= cnt - 1;
            elsif(Dir = '1') then
                cnt <= cnt + 1;
            else null;
            end if;
        else null;

        end if;

    end process;

    COUNT <= std_ulogic_vector(cnt);


end architecture;

Combinational/counters/async/updown_counter/counter_tb.vhd
library ieee;
use ieee.std_logic_1164.all;
use ieee.numeric_std.all;


entity counter_tb is
end entity;

architecture testbench of counter_tb is

component counter
port
(
    Clk_in, Rst, Dir : in std_logic;
    COUNT: out std_ulogic_vector(3 downto 0)
);
end component;

signal clk_in, rst, dir: std_logic;
signal cnt: std_ulogic_vector(3 downto 0);

begin

    UUT : counter port map
    (
        Clk_in => clk_in,
        Rst => rst,
        Dir => dir,
        COUNT => cnt
    );


    stim_proc : process
    begin
        rst<='1';
        dir<='1';
        wait for 160 ns;
        dir <= '0';
        wait;


    end process;

    clock: process
    begin
        dir <= '1';
        for ii in 1 to 8 loop
            clk_in <= '0';
            wait for 10 ns;
            clk_in <= '1';
            wait for 10 ns;
        end loop;

        dir <='0';
        for jj in 1 to 8 loop
            clk_in <= '0';
            wait for 10 ns;
            clk_in <= '1';
            wait for 10 ns;
        end loop;

        wait;
    end process;



end architecture;

Combinational/counters/async/updown_counter/counter.vcd
$date
  Mon Mar 15 20:41:58 2021
$end
$version
  GHDL v0
$end
$timescale
  1 fs
$end
$scope module standard $end
$upscope $end
$scope module std_logic_1164 $end
$upscope $end
$scope module numeric_std $end
$upscope $end
$scope module counter_tb $end
$var reg 1 ! clk_in $end
$var reg 1 " rst $end
$var reg 1 # dir $end
$var reg 4 $ cnt[3:0] $end
$scope module uut $end
$var reg 1 % clk_in $end
$var reg 1 & rst $end
$var reg 1 ' dir $end
$var reg 4 ( count[3:0] $end
$var reg 4 ) cnt[3:0] $end
$upscope $end
$upscope $end
$enddefinitions $end
#0
0!
1"
1#
b0000 $
0%
1&
1'
b0000 (
b0000 )
#10000000
1!
1%
#20000000
0!
b0001 $
0%
b0001 (
b0001 )
#30000000
1!
1%
#40000000
0!
b0010 $
0%
b0010 (
b0010 )
#50000000
1!
1%
#60000000
0!
b0011 $
0%
b0011 (
b0011 )
#70000000
1!
1%
#80000000
0!
b0100 $
0%
b0100 (
b0100 )
#90000000
1!
1%
#100000000
0!
b0101 $
0%
b0101 (
b0101 )
#110000000
1!
1%
#120000000
0!
b0110 $
0%
b0110 (
b0110 )
#130000000
1!
1%
#140000000
0!
b0111 $
0%
b0111 (
b0111 )
#150000000
1!
1%
#160000000
0!
0#
b0110 $
0%
0'
b0110 (
b0110 )
#170000000
1!
1%
#180000000
0!
b0101 $
0%
b0101 (
b0101 )
#190000000
1!
1%
#200000000
0!
b0100 $
0%
b0100 (
b0100 )
#210000000
1!
1%
#220000000
0!
b0011 $
0%
b0011 (
b0011 )
#230000000
1!
1%
#240000000
0!
b0010 $
0%
b0010 (
b0010 )
#250000000
1!
1%
#260000000
0!
b0001 $
0%
b0001 (
b0001 )
#270000000
1!
1%
#280000000
0!
b0000 $
0%
b0000 (
b0000 )
#290000000
1!
1%
#300000000
0!
b1111 $
0%
b1111 (
b1111 )
