Seq_logic/T_flipflop/T_ff.vhd
library ieee;
use ieee.std_logic_1164.all;


entity T_ff is
    port
    (
        T, CLK, RST : in std_logic;
        Q, Qbar : out std_logic
    );
end entity;

architecture behavioural of T_ff is
begin

    process(CLK,RST) is
    variable m : std_logic := '0';
    begin
        if(RST = '1') then m:='0';
        elsif(falling_edge(CLK)) then
            if(T = '0') then m:=m;
            elsif(T = '1') then m:= not m;
            else null;
            end if;
        end if;

        Q <= m;
        Qbar <= not m;
        
    end process;

 

end architecture;

counters/async/up_counter/up_counter.vhd
library ieee;
use ieee.std_logic_1164.all;

entity up_counter is
    port
    (
        Clk_in, Rst : in std_logic;
        Q, Qbar : out std_logic_vector(3 downto 0)
    );
end entity;

architecture dataflow of up_counter is

component T_ff
    port
    (
        T, CLK, RST : in std_logic;
        Q, Qbar : out std_logic
    );

end component;


signal t : std_logic_vector(3 downto 0) := "1111";
signal qff: std_logic_vector(3 downto 0);

begin

    ff1 : T_ff port map
        (
            T => t(0),
            CLK => Clk_in,
            RST => Rst,
            Q => qff(0),
            Qbar => Qbar(0)
        );

    ff2 : T_ff port map
        (
            T => t(1),
            CLK => qff(0),
            RST => Rst,
            Q => qff(1),
            Qbar => Qbar(1)
        );

    ff3 : T_ff port map
        (
            T => t(2),
            CLK => qff(1),
            RST => Rst,
            Q => qff(2),
            Qbar => Qbar(2)
        );
    
    ff4 : T_ff port map
        (
            T => t(3),
            CLK => qff(2),
            RST => Rst,
            Q => qff(3),
            Qbar => Qbar(3)
        );

    Q <= qff;



end architecture;

counters/async/up_counter/up_counter_tb.vhd
library ieee;
use ieee.std_logic_1164.all;

entity up_counter_tb is
end entity;

architecture testbench of up_counter_tb is

component up_counter
port
(
    Clk_in, Rst : in std_logic;
    Q, Qbar : out std_logic_vector(3 downto 0)
);
end component;

signal clk_in, rst: std_logic;
signal q, qbar: std_logic_vector(3 downto 0);

begin

    UUT : up_counter port map
    (
        Clk_in => clk_in,
        Rst => rst,
        Q => q,
        Qbar => qbar
    );

    rst <= '1';

    clock: process
    begin
        for ii in 1 to 7 loop
            clk_in <= '0';
            wait for 10 ns;
            clk_in <= '1';
            wait for 10 ns;
        end loop;

        wait;
    end process;



end architecture;

counters/async/up_counter/up_counter.vcd
$date
  Mon Mar 15 21:01:27 2021
$end
$version
  GHDL v0
$end
$timescale
  1 fs
$end
$scope module standard $end
$upscope $end
$scope module std_logic_1164 $end
$upscope $end
$scope module up_counter_tb $end
$var reg 1 ! clk_in $end
$var reg 1 " rst $end
$var reg 4 # q[3:0] $end
$var reg 4 $ qbar[3:0] $end
$scope module uut $end
$var reg 1 % clk_in $end
$var reg 1 & rst $end
$var reg 4 ' q[3:0] $end
$var reg 4 ( qbar[3:0] $end
$var reg 4 ) t[3:0] $end
$var reg 4 * qff[3:0] $end
$scope module ff1 $end
$var reg 1 + t $end
$var reg 1 , clk $end
$var reg 1 - rst $end
$var reg 1 . q $end
$var reg 1 / qbar $end
$upscope $end
$scope module ff2 $end
$var reg 1 0 t $end
$var reg 1 1 clk $end
$var reg 1 2 rst $end
$var reg 1 3 q $end
$var reg 1 4 qbar $end
$upscope $end
$scope module ff3 $end
$var reg 1 5 t $end
$var reg 1 6 clk $end
$var reg 1 7 rst $end
$var reg 1 8 q $end
$var reg 1 9 qbar $end
$upscope $end
$scope module ff4 $end
$var reg 1 : t $end
$var reg 1 ; clk $end
$var reg 1 < rst $end
$var reg 1 = q $end
$var reg 1 > qbar $end
$upscope $end
$upscope $end
$upscope $end
$enddefinitions $end
#0
0!
1"
b0000 #
b1111 $
0%
1&
b0000 '
b1111 (
b1111 )
b0000 *
1+
0,
1-
0.
1/
10
01
12
03
14
15
06
17
08
19
1:
0;
1<
0=
1>
#10000000
1!
1%
1,
#20000000
0!
b0001 #
b1110 $
0%
b0001 '
b1110 (
b0001 *
0,
1.
0/
11
#30000000
1!
1%
1,
#40000000
0!
b0010 #
b1101 $
0%
b0010 '
b1101 (
b0010 *
0,
0.
1/
01
13
04
16
#50000000
1!
1%
1,
#60000000
0!
b0011 #
b1100 $
0%
b0011 '
b1100 (
b0011 *
0,
1.
0/
11
#70000000
1!
1%
1,
#80000000
0!
b0100 #
b1011 $
0%
b0100 '
b1011 (
b0100 *
0,
0.
1/
01
03
14
06
18
09
1;
#90000000
1!
1%
1,
#100000000
0!
b0101 #
b1010 $
0%
b0101 '
b1010 (
b0101 *
0,
1.
0/
11
#110000000
1!
1%
1,
#120000000
0!
b0110 #
b1001 $
0%
b0110 '
b1001 (
b0110 *
0,
0.
1/
01
13
04
16
#130000000
1!
1%
1,
#140000000
0!
b0111 #
b1000 $
0%
b0111 '
b1000 (
b0111 *
0,
1.
0/
11
#150000000
1!
1%
1,
#160000000
0!
b1000 #
b0111 $
0%
b1000 '
b0111 (
b1000 *
0,
0.
1/
01
03
14
06
08
19
0;
1=
0>
#170000000
1!
1%
1,
#180000000
0!
b1001 #
b0110 $
0%
b1001 '
b0110 (
b1001 *
0,
1.
0/
11
#190000000
1!
1%
1,
#200000000
0!
b1010 #
b0101 $
0%
b1010 '
b0101 (
b1010 *
0,
0.
1/
01
13
04
16
#210000000
1!
1%
1,
#220000000
0!
b1011 #
b0100 $
0%
b1011 '
b0100 (
b1011 *
0,
1.
0/
11
#230000000
1!
1%
1,
#240000000
0!
b1100 #
b0011 $
0%
b1100 '
b0011 (
b1100 *
0,
0.
1/
01
03
14
06
18
09
1;
#250000000
1!
1%
1,
#260000000
0!
b1101 #
b0010 $
0%
b1101 '
b0010 (
b1101 *
0,
1.
0/
11
#270000000
1!
1%
1,
#280000000
0!
b1110 #
b0001 $
0%
b1110 '
b0001 (
b1110 *
0,
0.
1/
01
13
04
16
#290000000
1!
1%
1,
#300000000
0!
b1111 #
b0000 $
0%
b1111 '
b0000 (
b1111 *
0,
1.
0/
11
